webdriver_manager_zh/__init__.py
webdriver_manager_zh/chrome.py
webdriver_manager_zh/firefox.py
webdriver_manager_zh/microsoft.py
webdriver_manager_zh/opera.py
webdriver_manager_zh/py.typed
webdriver_manager_zh/core/__init__.py
webdriver_manager_zh/core/archive.py
webdriver_manager_zh/core/config.py
webdriver_manager_zh/core/constants.py
webdriver_manager_zh/core/download_manager.py
webdriver_manager_zh/core/driver.py
webdriver_manager_zh/core/driver_cache.py
webdriver_manager_zh/core/file_manager.py
webdriver_manager_zh/core/http.py
webdriver_manager_zh/core/logger.py
webdriver_manager_zh/core/manager.py
webdriver_manager_zh/core/os_manager.py
webdriver_manager_zh/core/utils.py
webdriver_manager_zh/drivers/__init__.py
webdriver_manager_zh/drivers/chrome.py
webdriver_manager_zh/drivers/edge.py
webdriver_manager_zh/drivers/firefox.py
webdriver_manager_zh/drivers/ie.py
webdriver_manager_zh/drivers/opera.py
webdriver_manager_zh-4.0.3.dist-info/LICENSE
webdriver_manager_zh-4.0.3.dist-info/METADATA
webdriver_manager_zh-4.0.3.dist-info/WHEEL
webdriver_manager_zh-4.0.3.dist-info/top_level.txt
webdriver_manager_zh-4.0.3.dist-info/RECORD
