Metadata-Version: 2.1
Name: webdriver_manager_zh
Version: 4.0.3
Summary: Library provides the way to automatically manage drivers for different browsers
Home-page: https://github.com/SergeyPirogov/webdriver_manager
Requires-Python: >=3.7
License-File: LICENSE
Requires-Dist: requests
Requires-Dist: python-dotenv
Requires-Dist: packaging
